movid-0.1.0.dist-info/METADATA
movid-0.1.0.dist-info/WHEEL
movid-0.1.0.dist-info/entry_points.txt
movid/__init__.py
movid-0.1.0.dist-info/RECORD
