Metadata-Version: 2.1
Name: movid
Version: 0.1.0
Summary: Default template for PDM package
Author-Email: Ankit Anand <ankit0.anand0@gmail.com>
License: MIT
Requires-Python: >=3.10
